LICENSE
MANIFEST.in
README.md
README.rst
setup.py
pushscreen/__init__.py
pushscreen/channel.py
pushscreen/cli.py
pushscreen/utils.py
pushscreen.egg-info/PKG-INFO
pushscreen.egg-info/SOURCES.txt
pushscreen.egg-info/dependency_links.txt
pushscreen.egg-info/entry_points.txt
pushscreen.egg-info/requires.txt
pushscreen.egg-info/top_level.txt