Metadata-Version: 1.0
Name: pushscreen
Version: 0.3.0
Summary: Python client for pushscreen.io
Home-page: http://pushscreen.io/
Author: Philipp Bosch
Author-email: hello@pb.io
License: Copyright (c) 2012 Philipp Bosch.
